cloudsend/__init__.py
cloudsend/aws.py
cloudsend/cli.py
cloudsend/combopt.py
cloudsend/config_state.py
cloudsend/core.py
cloudsend/demo.py
cloudsend/maestroclient.py
cloudsend/maestroserver.py
cloudsend/provider.py
cloudsend/providerfat.py
cloudsend/providerlight.py
cloudsend/resources/instancetypes-aws.csv
cloudsend/resources/remote_files/bootstrap.sh
cloudsend/resources/remote_files/config.py
cloudsend/resources/remote_files/env_check.py
cloudsend/resources/remote_files/env_state.sh
cloudsend/resources/remote_files/getpid.sh
cloudsend/resources/remote_files/kill.sh
cloudsend/resources/remote_files/maestroenv.sh
cloudsend/resources/remote_files/microrun.sh
cloudsend/resources/remote_files/reset.sh
cloudsend/resources/remote_files/resetmaestro.sh
cloudsend/resources/remote_files/run.sh
cloudsend/resources/remote_files/startmaestro.sh
cloudsend/resources/remote_files/startserver.sh
cloudsend/resources/remote_files/state.sh
cloudsend/resources/remote_files/tail.sh
cloudsend/resources/remote_files/waitmaestro.sh
cloudsend/scriptflow/runner.py
cloudsend/utils.py
requirements.txt
cloudsend-0.6.5.dist-info/entry_points.txt
cloudsend-0.6.5.dist-info/WHEEL
cloudsend-0.6.5.dist-info/METADATA
cloudsend-0.6.5.dist-info/RECORD
